hauntedhouse/__init__.py
hauntedhouse/client.py
hauntedhouse/py.typed
hauntedhouse-0.1.10.dist-info/METADATA
hauntedhouse-0.1.10.dist-info/WHEEL
hauntedhouse-0.1.10.dist-info/top_level.txt
hauntedhouse-0.1.10.dist-info/RECORD
