Metadata-Version: 2.1
Name: hauntedhouse
Version: 0.1.10
Summary: Client for hauntedhouse yara search engine.
License: MIT Licence
Requires-Python: >=3.9
Requires-Dist: requests
Requires-Dist: websockets
